ccpl/__init__.py
ccpl/console.py
ccpl/help.py
ccpl/setup.py
ccpl/scripts/__init__.py
ccpl/scripts/createwebproject.py
ccpl/scripts/ytdownloader.py
ccpl-0.1.18.dist-info/LICENSE
ccpl-0.1.18.dist-info/METADATA
ccpl-0.1.18.dist-info/WHEEL
ccpl-0.1.18.dist-info/top_level.txt
ccpl-0.1.18.dist-info/RECORD
