Metadata-Version: 2.1
Name: ccpl
Version: 0.1.18
Summary: ColorfulCore Python Library - CCPL for short.
Home-page: http://www.rainbowdoge.000webhostapp.com
Author: Rainbow Doge
Author-email: realrainbowdoge@gmail.com
License: UNKNOWN
Platform: UNKNOWN
Classifier: Programming Language :: Python :: 3
Classifier: License :: OSI Approved :: MIT License
Classifier: Operating System :: OS Independent
